sysdash/__init__.py
sysdash/sysdash.py
sysdash-0.3.dist-info/METADATA
sysdash-0.3.dist-info/WHEEL
sysdash-0.3.dist-info/entry_points.txt
sysdash-0.3.dist-info/top_level.txt
sysdash-0.3.dist-info/RECORD
