Metadata-Version: 2.1
Name: sysdash
Version: 0.3
Summary: System information utility
Home-page: https://github.com/Spandan7724/sysdash
Author: Spandan Chavan
Author-email: spandanchavan727477@gmail.com
Classifier: Programming Language :: Python :: 3
Classifier: License :: OSI Approved :: MIT License
Classifier: Operating System :: OS Independent
Requires-Dist: psutil
Requires-Dist: GPUtil
Requires-Dist: uptime
Requires-Dist: rich
Requires-Dist: py-cpuinfo
Requires-Dist: wmi
Requires-Dist: screeninfo
